pymeli/__init__.py
pymeli/pymeli.py
pymeli-0.2.8.dist-info/LICENSE
pymeli-0.2.8.dist-info/METADATA
pymeli-0.2.8.dist-info/WHEEL
pymeli-0.2.8.dist-info/top_level.txt
pymeli-0.2.8.dist-info/RECORD
