Metadata-Version: 2.1
Name: pymeli
Version: 0.2.8
Summary: A nice SDK for Mercado Libre
Author: Ernesto Monroy
License: MIT License
Project-URL: Homepage, https://github.com/labrixdigital/pymeli
Project-URL: Bug Tracker, https://github.com/labrixdigital/pymeli/issues
Keywords: meli,mercado libre,sdk
Classifier: Programming Language :: Python :: 3
Classifier: License :: OSI Approved :: MIT License
Classifier: Operating System :: OS Independent
Classifier: Intended Audience :: Developers
Classifier: Development Status :: 3 - Alpha
Classifier: Topic :: Utilities
Requires-Python: >=3.5
License-File: LICENSE
Requires-Dist: requests
Requires-Dist: requests-toolbelt
